vision_loom/__init__.py
vision_loom/models/grounding_dino.py
vision_loom/utils/io.py
vision_loom-0.1.dist-info/licenses/LICENSE
vision_loom-0.1.dist-info/METADATA
vision_loom-0.1.dist-info/WHEEL
vision_loom-0.1.dist-info/top_level.txt
vision_loom-0.1.dist-info/RECORD
