Metadata-Version: 2.4
Name: vision-loom
Version: 0.1
Summary: Framework to create labeling data from VLM and other larger models for computer vision tasks
Author-email: Prishanga Bora <prishanga1@gmail.com>
Requires-Python: >=3.10
License-File: LICENSE
Requires-Dist: torch<3.0,>=2.1
Requires-Dist: torchvision<1.0,>=0.16
Requires-Dist: transformers<6.0,>=4.40
Requires-Dist: accelerate<2.0,>=0.30
Requires-Dist: tokenizers<1.0,>=0.15
Requires-Dist: safetensors<1.0,>=0.4
Requires-Dist: huggingface_hub<2.0,>=0.20
Requires-Dist: numpy<3.0,>=1.26
Requires-Dist: networkx<4.0,>=3.0
Requires-Dist: sympy<2.0,>=1.12
Requires-Dist: mpmath<2.0,>=1.3
Requires-Dist: pillow<13.0,>=10.0
Requires-Dist: PyYAML<7.0,>=6.0
Requires-Dist: regex>=2023.0
Requires-Dist: tqdm<5.0,>=4.65
Requires-Dist: filelock<4.0,>=3.12
Requires-Dist: fsspec<2027.0,>=2024.0
Requires-Dist: httpx<1.0,>=0.25
Requires-Dist: httpcore<2.0,>=1.0
Requires-Dist: anyio<5.0,>=4.0
Requires-Dist: certifi
Requires-Dist: idna
Dynamic: license-file
